setup.py
influxdbnagiosplugin/__init__.py
influxdbnagiosplugin/main.py
influxdbnagiosplugin/query.py
influxdbnagiosplugin/resources.py
influxdbnagiosplugin/summaries.py
influxdbnagiosplugin.egg-info/PKG-INFO
influxdbnagiosplugin.egg-info/SOURCES.txt
influxdbnagiosplugin.egg-info/dependency_links.txt
influxdbnagiosplugin.egg-info/entry_points.txt
influxdbnagiosplugin.egg-info/requires.txt
influxdbnagiosplugin.egg-info/top_level.txt