Metadata-Version: 1.0
Name: influxdbnagiosplugin
Version: 1.4
Summary: InfluxDB Nagios Plugin
Home-page: http://locationlabs.com
Author: Location Labs
Author-email: info@locationlabs.com
License: UNKNOWN
Platform: UNKNOWN
